[
    {
      "id": 1,
      "description": "O 1Tostão foi bem prático e simples de se utilizar, simplesmente adorei a minha experiência com o site.",
      "name": "Murilo Simões",
      "img": "assets/img/murilo.png",
      "alt": "Murilo"
    },
    {
      "id": 2,
      "description": "Eu pensava que para ganhar dinheiro precisava de uma empresa, mas com o 1Tostão as empresas precisam de mim.",
      "name": "Kaio Esposito",
      "img": "assets/img/kaioba.png",
      "alt": "Kaioba"

    },
    {
      "id": 3,
      "description": "Hoje em dia só utilizo o 1Tostão de site de Freelance, não tem nenhum mais simples e que valha mais a pena que o 1Tostão.",
      "name": "Victor Hugo",
      "img": "assets/img/champs.png",
      "alt": "Victor"
    }
  ]